yc_pyvisa/__init__.py
yc_pyvisa/model_II.dll
yc_pyvisa-0.1.0.dist-info/METADATA
yc_pyvisa-0.1.0.dist-info/WHEEL
yc_pyvisa-0.1.0.dist-info/top_level.txt
yc_pyvisa-0.1.0.dist-info/RECORD
